COPYING
MANIFEST.in
Makefile
README
aioeventlet.py
run_aiotest.py
runtests.py
setup.py
tox.ini
aioeventlet.egg-info/PKG-INFO
aioeventlet.egg-info/SOURCES.txt
aioeventlet.egg-info/dependency_links.txt
aioeventlet.egg-info/requires.txt
aioeventlet.egg-info/top_level.txt
doc/Makefile
doc/changelog.rst
doc/conf.py
doc/index.rst
doc/make.bat
doc/openstack.rst
doc/poplar_hawk-moth.jpg
doc/status.rst
doc/using.rst
tests/__init__.py
tests/test_eventlet.py
tests/test_greenlet.py