Metadata-Version: 1.1
Name: aioeventlet
Version: 0.5.1
Summary: asyncio event loop scheduling callbacks in eventlet.
Home-page: http://aioeventlet.readthedocs.org/
Author: Victor Stinner
Author-email: victor.stinner@gmail.com
License: Apache License 2.0
Platform: UNKNOWN
Classifier: Programming Language :: Python
Classifier: Programming Language :: Python :: 3
Classifier: License :: OSI Approved :: Apache Software License
